tmktthreader/__init__.py
tmktthreader/async_threader.py
tmktthreader/threader.py
tmktthreader-1.0.1.dist-info/METADATA
tmktthreader-1.0.1.dist-info/WHEEL
tmktthreader-1.0.1.dist-info/LICENSE
tmktthreader-1.0.1.dist-info/RECORD
