Metadata-Version: 2.1
Name: tmktthreader
Version: 1.0.1
Summary: 
License: apache 2.0
Author: ladettanguy
Author-email: sti2dlab.ladettanguy@gmail.com
Requires-Python: >=3.10,<4.0
Classifier: License :: Other/Proprietary License
Classifier: Programming Language :: Python :: 3
Classifier: Programming Language :: Python :: 3.10
Classifier: Programming Language :: Python :: 3.11
